com_vitalai_domain_wordnet/__init__.py
com_vitalai_domain_wordnet/domain-ontology/vital-wordnet-0.2.304.owl
com_vitalai_domain_wordnet/model/AdjectiveSynsetNode.py
com_vitalai_domain_wordnet/model/AdjectiveSynsetNode.pyi
com_vitalai_domain_wordnet/model/AdverbSynsetNode.py
com_vitalai_domain_wordnet/model/AdverbSynsetNode.pyi
com_vitalai_domain_wordnet/model/DomainOntology.py
com_vitalai_domain_wordnet/model/Edge_WordnetAlsoSee.py
com_vitalai_domain_wordnet/model/Edge_WordnetAlsoSee.pyi
com_vitalai_domain_wordnet/model/Edge_WordnetAntonym.py
com_vitalai_domain_wordnet/model/Edge_WordnetAntonym.pyi
com_vitalai_domain_wordnet/model/Edge_WordnetAttribute.py
com_vitalai_domain_wordnet/model/Edge_WordnetAttribute.pyi
com_vitalai_domain_wordnet/model/Edge_WordnetCause.py
com_vitalai_domain_wordnet/model/Edge_WordnetCause.pyi
com_vitalai_domain_wordnet/model/Edge_WordnetDerivationallyRelatedForm.py
com_vitalai_domain_wordnet/model/Edge_WordnetDerivationallyRelatedForm.pyi
com_vitalai_domain_wordnet/model/Edge_WordnetDerivedFromAdjective.py
com_vitalai_domain_wordnet/model/Edge_WordnetDerivedFromAdjective.pyi
com_vitalai_domain_wordnet/model/Edge_WordnetDomainOfSynset_Region.py
com_vitalai_domain_wordnet/model/Edge_WordnetDomainOfSynset_Region.pyi
com_vitalai_domain_wordnet/model/Edge_WordnetDomainOfSynset_Topic.py
com_vitalai_domain_wordnet/model/Edge_WordnetDomainOfSynset_Topic.pyi
com_vitalai_domain_wordnet/model/Edge_WordnetDomainOfSynset_Usage.py
com_vitalai_domain_wordnet/model/Edge_WordnetDomainOfSynset_Usage.pyi
com_vitalai_domain_wordnet/model/Edge_WordnetEntailment.py
com_vitalai_domain_wordnet/model/Edge_WordnetEntailment.pyi
com_vitalai_domain_wordnet/model/Edge_WordnetHypernym.py
com_vitalai_domain_wordnet/model/Edge_WordnetHypernym.pyi
com_vitalai_domain_wordnet/model/Edge_WordnetHyponym.py
com_vitalai_domain_wordnet/model/Edge_WordnetHyponym.pyi
com_vitalai_domain_wordnet/model/Edge_WordnetInstanceHypernym.py
vital_ai_wordnet-0.1.5.dist-info/LICENSE
vital_ai_wordnet-0.1.5.dist-info/METADATA
vital_ai_wordnet-0.1.5.dist-info/WHEEL
vital_ai_wordnet-0.1.5.dist-info/entry_points.txt
vital_ai_wordnet-0.1.5.dist-info/top_level.txt
vital_ai_wordnet-0.1.5.dist-info/RECORD
